Metadata-Version: 2.1
Name: gradio-fastapi
Version: 0.1.0
Summary: Easily Share and Demo Your FastAPI Apps using Gradio Public URL Tunneling
Home-page: https://github.com/HishamYahya/gradio-fastapi
Download-URL: https://github.com/HishamYahya/gradio-fastapi/archive/refs/tags/v0.1.0.tar.gz
Author: Hisham Alyahya
Author-email: Hishamaalyahya@gmail.com
License: MIT
Keywords: Gradio,Deployment,FastAPI,Server,Demoing,Backend,Frontend,Serving
Classifier: Development Status :: 3 - Alpha
Classifier: Intended Audience :: Developers
Classifier: Topic :: Internet
Classifier: Topic :: Software Development :: Build Tools
Classifier: Topic :: Software Development :: Libraries :: Python Modules
Classifier: License :: OSI Approved :: MIT License
Classifier: Programming Language :: Python :: 3
License-File: LICENSE
Requires-Dist: fastapi
